keyvi-0.7.3.dist-info/RECORD
keyvi-0.7.3.dist-info/WHEEL
keyvi-0.7.3.dist-info/top_level.txt
keyvi-0.7.3.dist-info/METADATA
keyvi-0.7.3.dist-info/licenses/LICENSE.txt
keyvi/_version.py
keyvi/__init__.py
keyvi/_core.cpython-311-darwin.so
keyvi/util/__init__.py
keyvi/completion/__init__.py
keyvi/cli/__init__.py
keyvi/cli/cli.py
keyvi/.dylibs/libsnappy.1.2.2.dylib
keyvi/.dylibs/libboost_thread.dylib
keyvi/.dylibs/libboost_iostreams.dylib
keyvi/.dylibs/libicudata.77.1.dylib
keyvi/.dylibs/libboost_container.dylib
keyvi/.dylibs/libicuuc.77.1.dylib
keyvi/.dylibs/libboost_process.dylib
keyvi/.dylibs/libboost_random.dylib
keyvi/.dylibs/libboost_regex.dylib
keyvi/.dylibs/libboost_program_options.dylib
keyvi/.dylibs/libboost_filesystem.dylib
keyvi/.dylibs/liblzma.5.dylib
keyvi/.dylibs/libboost_atomic.dylib
keyvi/.dylibs/libboost_date_time.dylib
keyvi/.dylibs/libicui18n.77.1.dylib
keyvi/.dylibs/libzstd.1.5.7.dylib
keyvi/.dylibs/libboost_chrono.dylib
keyvi/.dylibs/libboost_context.dylib
keyvi/dictionary/__init__.py
keyvi/index/__init__.py
keyvi/_pycore/keyvimerger.py
keyvi/_pycore/__init__.py
keyvi/vector/__init__.py
keyvi/compiler/__init__.py
keyvi-0.7.3.data/scripts/keyvi
