Metadata-Version: 2.1
Name: keyvi
Version: 0.7.3
Summary: Python package for keyvi
Home-page: http://keyvi.org
Download-URL: https://github.com/KeyviDev/keyvi/tarball/v0.7.3
Author: Hendrik Muhs
Author-email: hendrik.muhs@gmail.com
License: ASL 2.0
Keywords: FST
Classifier: Programming Language :: C++
Classifier: Programming Language :: Cython
Classifier: Programming Language :: Python
Classifier: Programming Language :: Python :: 3.9
Classifier: Programming Language :: Python :: 3.10
Classifier: Programming Language :: Python :: 3.11
Classifier: Programming Language :: Python :: 3.12
Classifier: Programming Language :: Python :: 3.13
Classifier: Programming Language :: Python :: Implementation :: CPython
Classifier: Programming Language :: Python :: Implementation :: PyPy
Classifier: Operating System :: MacOS :: MacOS X
Classifier: Operating System :: Unix
License-File: LICENSE.txt
